{
  "id": "36rdttk8ao",
  "category": "music",
  "title": "音楽缶▽ＳＵＲＦＡＣＥ▽韻シスト▽サカナクション▽宮本浩次",
  "fullTitle": "音楽缶▽ＳＵＲＦＡＣＥ▽韻シスト▽サカナクション▽宮本浩次",
  "detail": "最新のミュージックビデオをノーカットで紹介\n◇おしらせ\n詳しくはＨＰをチェック！\r\nhttp://www.tvk-yokohama.com/ongakukan/index2.php",
  "start": 1566410400000,
  "end": 1566411900000,
  "seconds": 1500,
  "description": "最新のミュージックビデオをノーカットで紹介",
  "extra": {
    "おしらせ": "詳しくはＨＰをチェック！\r\nhttp://www.tvk-yokohama.com/ongakukan/index2.php"
  },
  "channel": {
    "type": "GR",
    "channel": "31",
    "name": "ｔｖｋ１",
    "id": "1hjjdzs",
    "sid": 24632,
    "nid": 32375,
    "hasLogoData": true,
    "n": 5
  },
  "subTitle": "",
  "episode": null,
  "flags": []
}
