{
  "id": "idud3qb",
  "category": "variety",
  "title": "斎藤工×板谷由夏　映画工房　＃６１８",
  "fullTitle": "🈚🈠斎藤工×板谷由夏　映画工房　＃６１８",
  "detail": "◇番組名\n斎藤工×板谷由夏　映画工房　＃６１８　「Ｔｏ　Ｌｅｓｌｉｅ　トゥ・レスリー」ほか\n◇番組内容\n映画専門チャンネルＷＯＷＯＷシネマがおくるこだわりの映画特集などを「映画は生活の一部」と語る俳優・斎藤工と板谷由夏が深く掘り下げる映画情報番組\n◇番組内容２\n■斎藤工と板谷由夏が選ぶ今週のＰＩＣＫ　ＵＰ！\r\n「Ｔｏ　Ｌｅｓｌｉｅ　トゥ・レスリー」１１／１７（金）午後１１：００\r\n　\r\n■ゆかいな映画仲間。　　ゲスト：樋口真嗣監督\r\n「シン・ウルトラマン」１１／１８（土）午後８：００\n◇出演／関連情報\n（日本）\r\n【出演】斎藤工、板谷由夏",
  "start": 1699619400000,
  "end": 1699620300000,
  "seconds": 900,
  "description": "",
  "extra": {
    "番組名": "斎藤工×板谷由夏　映画工房　＃６１８　「Ｔｏ　Ｌｅｓｌｉｅ　トゥ・レスリー」ほか",
    "番組内容": "映画専門チャンネルＷＯＷＯＷシネマがおくるこだわりの映画特集などを「映画は生活の一部」と語る俳優・斎藤工と板谷由夏が深く掘り下げる映画情報番組",
    "番組内容２": "■斎藤工と板谷由夏が選ぶ今週のＰＩＣＫ　ＵＰ！\r\n「Ｔｏ　Ｌｅｓｌｉｅ　トゥ・レスリー」１１／１７（金）午後１１：００\r\n　\r\n■ゆかいな映画仲間。　　ゲスト：樋口真嗣監督\r\n「シン・ウルトラマン」１１／１８（土）午後８：００",
    "出演／関連情報": "（日本）\r\n【出演】斎藤工、板谷由夏"
  },
  "channel": {
    "type": "BS",
    "channel": "BS03_0",
    "name": "ＷＯＷＯＷプライム",
    "id": "8ksf",
    "sid": 191,
    "nid": 4,
    "hasLogoData": true,
    "n": 60
  },
  "subTitle": "",
  "episode": 618,
  "flags": [
    "無",
    "初"
  ]
}
