{
  "id": "idtr35u",
  "category": "variety",
  "title": "サンド道楽　／磁石がマイナースポーツを提案！斬新弓矢対決＆へディスとは？",
  "fullTitle": "サンド道楽　＃7／磁石がマイナースポーツを提案！斬新弓矢対決＆へディスとは？",
  "detail": "多忙で無趣味なサンドウィッチマンに磁石がマイナースポーツを提案！斬新弓矢対決＆ヘディング×卓球「へディス」に迫る！",
  "start": 1626012000000,
  "end": 1626013800000,
  "seconds": 1800,
  "channel": {
    "type": "BS",
    "channel": "BS13_1",
    "name": "ＢＳフジ・１８１",
    "id": "8ks5",
    "sid": 181,
    "nid": 4,
    "hasLogoData": false,
    "n": 56
  },
  "subTitle": "へディス",
  "episode": 7,
  "flags": []
}
