{
  "id": "w66ocqa",
  "category": "drama",
  "title": "[5.1]オール・ライズ 判事ローラ・カーマイケル",
  "fullTitle": "[字][5.1]オール・ライズ 判事ローラ・カーマイケル(帯)#1[新]",
  "detail": "#1「ローラ判事誕生」\r\nPilot\r\n地方検事補ローラ・カーマイケルは、念願叶ってロサンゼルス郡上級裁判所判事に任命された。",
  "start": 1636113600000,
  "end": 1636117200000,
  "seconds": 3600,
  "channel": {
    "type": "CS",
    "channel": "CS14",
    "name": "スーパー！ドラマＴＶ",
    "id": "f0d2",
    "sid": 310,
    "nid": 7,
    "hasLogoData": true,
    "n": 115
  },
  "subTitle": "ローラ判事誕生",
  "episode": 1,
  "flags": [
    "字",
    "新"
  ]
}
