{
  "id": "idozsew",
  "category": "sports",
  "title": "カーリング女子世界選手権２０２３　予選リーグ「日本」対「スコットランド」",
  "fullTitle": "カーリング女子世界選手権２０２３　予選リーグ「日本」対「スコットランド」",
  "detail": "【解説】市川美余，【アナウンサー】金城均　～スウェーデン・サンドビーケンから中継～\n◇出演者\n【解説】市川美余，【アナウンサー】金城均",
  "start": 1679248800000,
  "end": 1679259600000,
  "seconds": 10800,
  "description": "【解説】市川美余，【アナウンサー】金城均　～スウェーデン・サンドビーケンから中継～",
  "extra": {
    "出演者": "【解説】市川美余，【アナウンサー】金城均"
  },
  "channel": {
    "type": "BS",
    "channel": "BS15_0",
    "name": "ＮＨＫＢＳ１",
    "id": "8kpx",
    "sid": 101,
    "nid": 4,
    "hasLogoData": true,
    "n": 41
  },
  "subTitle": "スコットランド",
  "episode": 1,
  "flags": []
}
