{
  "id": "idrywjg",
  "category": "drama",
  "title": "山村美紗サスペンス　狩矢父娘シリーズ",
  "fullTitle": "[字]山村美紗サスペンス　狩矢父娘シリーズ",
  "detail": "「京都・美人女優連続殺人事件 主役は2度殺される!?ガラス張りの密室殺人トリックを“股のぞき”が暴く」▽テレビ朝日系列で2010年に放送された第11シリーズ\n◇番組内容\n捜査一課・狩矢警部の娘・和美は、編集プロダクションの記者兼カメラマン。ある日、和美は映画の主演女優・愛川有紀の取材でロケ現場に出かけた。だが取材中、有紀が相手役の鷹崎達也と倒れこむシーンの撮影で突然苦悶し絶命してしまうという騒ぎに遭遇する。捜査の結果、死因は毒針が背中に刺さったことによるものと判明。毒針を仕込んだ人物は誰を狙ったのだろうか。その後、代役に抜擢された女優・中里みなみも謎の死を遂げ…。\n◇出演者\n藤谷美紀、田村亮、原田龍二、山村紅葉、宮本真希、小沢真珠、高橋光臣、小野麻亜矢、山内明日、中野良子 ほか\n◇番組ホームページ\n＜番組ホームページはこちら！＞\r\nwww.bs-asahi.co.jp/drama/\n◇制作\nテレビ朝日、東映",
  "start": 1624795200000,
  "end": 1624802040000,
  "seconds": 6840,
  "description": "「京都・美人女優連続殺人事件 主役は2度殺される!?ガラス張りの密室殺人トリックを“股のぞき”が暴く」▽テレビ朝日系列で2010年に放送された第11シリーズ",
  "extra": {
    "番組内容": "捜査一課・狩矢警部の娘・和美は、編集プロダクションの記者兼カメラマン。ある日、和美は映画の主演女優・愛川有紀の取材でロケ現場に出かけた。だが取材中、有紀が相手役の鷹崎達也と倒れこむシーンの撮影で突然苦悶し絶命してしまうという騒ぎに遭遇する。捜査の結果、死因は毒針が背中に刺さったことによるものと判明。毒針を仕込んだ人物は誰を狙ったのだろうか。その後、代役に抜擢された女優・中里みなみも謎の死を遂げ…。",
    "出演者": "藤谷美紀、田村亮、原田龍二、山村紅葉、宮本真希、小沢真珠、高橋光臣、小野麻亜矢、山内明日、中野良子 ほか",
    "番組ホームページ": "＜番組ホームページはこちら！＞\r\nwww.bs-asahi.co.jp/drama/",
    "制作": "テレビ朝日、東映"
  },
  "channel": {
    "type": "BS",
    "channel": "BS01_0",
    "name": "ＢＳ朝日１",
    "id": "8krb",
    "sid": 151,
    "nid": 4,
    "hasLogoData": false,
    "n": 47
  },
  "subTitle": "京都・美人女優連続殺人事件 主役は2度殺される!?ガラス張りの密室殺人トリックを“股のぞき”が暴く",
  "episode": null,
  "flags": [
    "字"
  ]
}
