{
  "id": "36h6jr1axm",
  "category": "drama",
  "title": "三ツ矢先生の計画的な餌付け。",
  "fullTitle": "三ツ矢先生の計画的な餌付け。🈑🅂",
  "detail": "第２話【山崎まさよし×酒井大成◆ドラマフィル】（字）\n◇番組概要\nイケメンのライバル編集者の登場に嫉妬と妄想が止まらない石田（酒井大成）。楽しみにしていた三ツ矢（山崎まさよし）からの手料理の申し出も意地を張って断ってしまいーー\n◇番組内容\nイケメンのライバル編集者・冬島（小南光司）の登場に嫉妬と妄想が止まらない石田（酒井大成）。楽しみにしていた三ツ矢（山崎まさよし）からの手料理の申し出も意地を張って断ってしまう。その後二人は、三ツ矢お気に入りの、シゲ（宇野祥平）のバーに行くことに。そこで石田の栄光と挫折の過去が明らかになる……。\n◇番組内容②\n店を出て帰ろうとする石田だったが、「石田くんにしかできへんことがあんねん」と三ツ矢に呼び止めれ……。少しずつ心の距離を縮める二人ーー。しかしそんな中、三ツ矢のことを「俺の恋人」と呼ぶ謎の男が現れ…！？\n◇出演者\n山崎まさよし　酒井大成　丸山智己　宇野祥平　川面千晶　三原羽衣　今森茉耶　ほか",
  "start": 1722870000000,
  "end": 1722873300000,
  "seconds": 3300,
  "description": "第２話【山崎まさよし×酒井大成◆ドラマフィル】（字）",
  "extra": {
    "番組概要": "イケメンのライバル編集者の登場に嫉妬と妄想が止まらない石田（酒井大成）。楽しみにしていた三ツ矢（山崎まさよし）からの手料理の申し出も意地を張って断ってしまいーー",
    "番組内容": "イケメンのライバル編集者・冬島（小南光司）の登場に嫉妬と妄想が止まらない石田（酒井大成）。楽しみにしていた三ツ矢（山崎まさよし）からの手料理の申し出も意地を張って断ってしまう。その後二人は、三ツ矢お気に入りの、シゲ（宇野祥平）のバーに行くことに。そこで石田の栄光と挫折の過去が明らかになる……。",
    "番組内容②": "店を出て帰ろうとする石田だったが、「石田くんにしかできへんことがあんねん」と三ツ矢に呼び止めれ……。少しずつ心の距離を縮める二人ーー。しかしそんな中、三ツ矢のことを「俺の恋人」と呼ぶ謎の男が現れ…！？",
    "出演者": "山崎まさよし　酒井大成　丸山智己　宇野祥平　川面千晶　三原羽衣　今森茉耶　ほか"
  },
  "channel": {
    "type": "GR",
    "channel": "32",
    "name": "テレ玉１",
    "id": "1hes13s",
    "sid": 29752,
    "nid": 32295,
    "hasLogoData": true,
    "n": 12
  },
  "subTitle": "山崎まさよし×酒井大成◆ドラマフィル",
  "episode": 2,
  "flags": [
    "字",
    "S"
  ]
}
