{
  "id": "w65li6z",
  "category": "drama",
  "title": "大岡越前 第3部 ［朝だよ！大岡越前］◆加藤剛／青柳美枝子",
  "fullTitle": "大岡越前 第3部 #27［朝だよ！大岡越前］◆加藤剛／青柳美枝子",
  "detail": "第27回「死の匂いのする花」本編48分-1972年・全31話-出演：加藤剛／竹脇無我　ゲスト：青柳美枝子★忠相と雪絵の息子への想いを感じさせる家庭での描写は必見。",
  "start": 1616007600000,
  "end": 1616011020000,
  "seconds": 3420,
  "channel": {
    "type": "CS",
    "channel": "CS4",
    "name": "時代劇専門ｃｈ",
    "id": "f0ck",
    "sid": 292,
    "nid": 7,
    "hasLogoData": false,
    "n": 100
  },
  "subTitle": "死の匂いのする花",
  "episode": 27,
  "flags": []
}
