{
  "id": "381jqz0crh",
  "category": "information",
  "title": "きょうの料理「はじめての手仕事」　かぶの甘酒漬け",
  "fullTitle": "きょうの料理「はじめての手仕事」　かぶの甘酒漬け🈑",
  "detail": "今回のテーマは、手軽でおいしい漬物。サラダ感覚の甘酒漬けから、野菜のもつ乳酸菌の力で発酵させるちょっと本格派のものまで。春めいたこの時季にぜひ挑戦してください！\n◇番組内容\nまずは、市販の甘酒でつくる「かぶの甘酒漬け」。セロリやにんじんでもつくることができる、上品な甘さの“べったら漬け”風です。続いては、塩もみした白菜を発酵させてつくる「発酵白菜」。ゆでた豚肉とあえたり、炒め物に入れたり、おかずにもなりますよ。最後は、漬け汁に漬けて発酵させるマイルドな辛みの「水キムチ」。漬け汁をスープにして冷麺風にするのもおすすめです。\n◇出演者\n【講師】榎本美沙，【司会】原大策",
  "start": 1678708800000,
  "end": 1678710300000,
  "seconds": 1500,
  "description": "今回のテーマは、手軽でおいしい漬物。サラダ感覚の甘酒漬けから、野菜のもつ乳酸菌の力で発酵させるちょっと本格派のものまで。春めいたこの時季にぜひ挑戦してください！",
  "extra": {
    "番組内容": "まずは、市販の甘酒でつくる「かぶの甘酒漬け」。セロリやにんじんでもつくることができる、上品な甘さの“べったら漬け”風です。続いては、塩もみした白菜を発酵させてつくる「発酵白菜」。ゆでた豚肉とあえたり、炒め物に入れたり、おかずにもなりますよ。最後は、漬け汁に漬けて発酵させるマイルドな辛みの「水キムチ」。漬け汁をスープにして冷麺風にするのもおすすめです。",
    "出演者": "【講師】榎本美沙，【司会】原大策"
  },
  "channel": {
    "type": "GR",
    "channel": "26",
    "name": "ＮＨＫＥテレ１東京",
    "id": "1i52rvs",
    "sid": 1032,
    "nid": 32737,
    "hasLogoData": true,
    "n": 2
  },
  "subTitle": "はじめての手仕事",
  "episode": 1,
  "flags": [
    "字"
  ]
}
