{
  "id": "ids0qnk",
  "category": "drama",
  "title": "ゴンゾウ～伝説の刑事　＃2「第一容疑者」",
  "fullTitle": "🈑ゴンゾウ～伝説の刑事　＃2「第一容疑者」",
  "detail": "鶴ともなみが撃たれた。死者が出たというが両方なのか1人だけなのか…。混乱の中、捜査本部に備品係の黒木が呼び戻される。呼び戻したのはかつての部下・佐久間だった…。",
  "start": 1715158800000,
  "end": 1715162400000,
  "seconds": 3600,
  "channel": {
    "type": "BS",
    "channel": "BS01_3",
    "name": "ＢＳ朝日２",
    "id": "8krc",
    "sid": 152,
    "nid": 4,
    "hasLogoData": true,
    "n": 49
  },
  "subTitle": "第一容疑者",
  "episode": 2,
  "flags": [
    "字"
  ]
}
