{
  "id": "36tfa8jc7h",
  "category": "variety",
  "title": "ＧＡＭＩＮＧ　ＨＯＵＳＥ　ＳＱＵＡＤ",
  "fullTitle": "ＧＡＭＩＮＧ　ＨＯＵＳＥ　ＳＱＵＡＤ",
  "detail": "ＡＰＥＸファン必見！ＧＨＳ　ＮＩＧＨＴ　エピソード５　ＥＬＬＹ軍ＶＳ板倉軍　招待プレイヤーが一挙振り返り！最悪のやらかしプレイ＆自分を褒めたい天才プレイは？",
  "start": 1665419700000,
  "end": 1665421500000,
  "seconds": 1800,
  "channel": {
    "type": "GR",
    "channel": "16",
    "name": "ＴＯＫＹＯ　ＭＸ１",
    "id": "1hkhnrt",
    "sid": 23609,
    "nid": 32391,
    "hasLogoData": true,
    "n": 35
  },
  "subTitle": "",
  "episode": 1,
  "flags": []
}
