{
  "id": "381f5ks5c7",
  "category": "information",
  "title": "明日へ１ｍｉｎ．　防災の知恵「長芋のお好み焼き」",
  "fullTitle": "明日へ１ｍｉｎ．　防災の知恵「長芋のお好み焼き」",
  "detail": "１分で学べる、いざという時に役に立つ防災の知恵「防災食レシピ」▽包丁いらず！栄養価が高く日持ちもする長芋を使ったお好み焼きの作り方を伝授\n◇出演者\n【語り】森田茉里恵\n◇番組内容\n１分で学べる、いざという時に役に立つ防災の知恵「防災食レシピ」▽包丁いらず！栄養価が高く日持ちもする長芋を使ったお好み焼きの作り方を伝授",
  "start": 1666244940000,
  "end": 1666245000000,
  "seconds": 60,
  "description": "１分で学べる、いざという時に役に立つ防災の知恵「防災食レシピ」▽包丁いらず！栄養価が高く日持ちもする長芋を使ったお好み焼きの作り方を伝授",
  "extra": {
    "出演者": "【語り】森田茉里恵",
    "番組内容": "１分で学べる、いざという時に役に立つ防災の知恵「防災食レシピ」▽包丁いらず！栄養価が高く日持ちもする長芋を使ったお好み焼きの作り方を伝授"
  },
  "channel": {
    "type": "GR",
    "channel": "27",
    "name": "ＮＨＫ総合１・東京",
    "id": "1i50mps",
    "sid": 1024,
    "nid": 32736,
    "hasLogoData": true,
    "n": 0
  },
  "subTitle": "長芋のお好み焼き",
  "episode": 1,
  "flags": []
}
