{
  "id": "381jqz05pu",
  "category": "information",
  "title": "趣味どきっ！　あの人の極上ハンバーグ",
  "fullTitle": "趣味どきっ！　あの人の極上ハンバーグ　[終]（９）「総集編」[解][字]",
  "detail": "今回はハンバーグシリーズの総集編。極上ハンバーグのオンパレードをおたのしみください。\n◇番組内容\n今回はハンバーグシリーズの総集編。＃１～＃８で紹介した極上ハンバーグを一挙振り返り。ハンバーグオンパレードをおたのしみください。\n◇出演者\n【語り】寺門ジモン，松村沙友理",
  "start": 1643200200000,
  "end": 1643201700000,
  "seconds": 1500,
  "description": "今回はハンバーグシリーズの総集編。極上ハンバーグのオンパレードをおたのしみください。",
  "extra": {
    "番組内容": "今回はハンバーグシリーズの総集編。＃１～＃８で紹介した極上ハンバーグを一挙振り返り。ハンバーグオンパレードをおたのしみください。",
    "出演者": "【語り】寺門ジモン，松村沙友理"
  },
  "channel": {
    "type": "GR",
    "channel": "26",
    "name": "ＮＨＫＥテレ１東京",
    "id": "1i52rvs",
    "sid": 1032,
    "nid": 32737,
    "hasLogoData": true,
    "n": 2
  },
  "subTitle": "総集編",
  "episode": 9,
  "flags": [
    "終",
    "解",
    "字"
  ]
}
