{
  "id": "36tfa8imgz",
  "category": "anime",
  "title": "Panty&Stocking with Garterbelt（再放送）CENSORED版　＃5",
  "fullTitle": "Panty&Stocking with Garterbelt（再放送）CENSORED版　＃5",
  "detail": "＃5「ハナムプトラ」「ヴォミッティング・ポイント」",
  "start": 1746633600000,
  "end": 1746635400000,
  "seconds": 1800,
  "channel": {
    "type": "GR",
    "channel": "16",
    "name": "ＴＯＫＹＯ　ＭＸ１",
    "id": "1hkhnrt",
    "sid": 23609,
    "nid": 32391,
    "hasLogoData": true,
    "n": 34
  },
  "subTitle": "ハナムプトラ",
  "episode": 5,
  "flags": []
}
