{
  "id": "381ocd85gl",
  "category": "variety",
  "title": "ノギザカスキッツ　ＡＣＴ２",
  "fullTitle": "ノギザカスキッツ　ＡＣＴ２＃３【スマイルガールズ③＆北川悠理教習所】",
  "detail": "乃木坂４６がさらば青春の光とコント▽パジャマで恋バナ！修学旅行の夜にスマイルガールズ登場！たんぽぽ白鳥を全力応援▽No.1不思議キャラをお勉強「北川悠理教習所」\n◇出演者\n乃木坂４６\r\nさらば青春の光\n◇番組内容\n乃木坂４６がコントに挑戦！共演は「キング・オブ・コント」ファイナリストさらば青春の光▽パジャマで恋バナ！修学旅行の夜にスマイルガールズ（柴田柚菜・清宮レイ・早川聖来・松尾美佑）登場！恋に奥手なたんぽぽ白鳥を全力応援！▽乃木坂No.1不思議キャラ北川悠理をお勉強！隠しカメラで撮影した北川悠理の不思議すぎる日常をクイズで出題…賀喜遥香の爆笑モノマネ▽佐藤楓の意外過ぎる特技とは？▽未公開映像はHuluで",
  "start": 1606148940000,
  "end": 1606150740000,
  "seconds": 1800,
  "description": "乃木坂４６がさらば青春の光とコント▽パジャマで恋バナ！修学旅行の夜にスマイルガールズ登場！たんぽぽ白鳥を全力応援▽No.1不思議キャラをお勉強「北川悠理教習所」",
  "extra": {
    "出演者": "乃木坂４６\r\nさらば青春の光",
    "番組内容": "乃木坂４６がコントに挑戦！共演は「キング・オブ・コント」ファイナリストさらば青春の光▽パジャマで恋バナ！修学旅行の夜にスマイルガールズ（柴田柚菜・清宮レイ・早川聖来・松尾美佑）登場！恋に奥手なたんぽぽ白鳥を全力応援！▽乃木坂No.1不思議キャラ北川悠理をお勉強！隠しカメラで撮影した北川悠理の不思議すぎる日常をクイズで出題…賀喜遥香の爆笑モノマネ▽佐藤楓の意外過ぎる特技とは？▽未公開映像はHuluで"
  },
  "channel": {
    "type": "GR",
    "channel": "12",
    "name": "日テレ１",
    "id": "1i54x1s",
    "sid": 1040,
    "nid": 32738,
    "hasLogoData": true,
    "n": 15
  },
  "subTitle": "スマイルガールズ③＆北川悠理教習所",
  "episode": 3,
  "flags": []
}
