{
  "id": "rksaawm",
  "category": "information",
  "title": "渡辺篤史の建もの探訪 #1565・1612・1657",
  "fullTitle": "渡辺篤史の建もの探訪 #1565・1612・1657",
  "detail": "#1565\r\n「店舗？ 事務所？ 超多目的住宅～東京都世田谷区・江頭邸」\r\n（テレビ朝日放送日:2020年5月23日）ほか",
  "start": 1652957700000,
  "end": 1652961600000,
  "seconds": 3900,
  "channel": {
    "type": "CS",
    "channel": "CS2",
    "name": "テレ朝チャンネル２",
    "id": "cv6z",
    "sid": 299,
    "nid": 6,
    "hasLogoData": true,
    "n": 108
  },
  "subTitle": "",
  "episode": 156,
  "flags": []
}
