{
  "id": "36l9gkuav0",
  "category": "drama",
  "title": "知ってるワイフ　第１２話",
  "fullTitle": "知ってるワイフ　第１２話🈑",
  "detail": "チソン×ハン・ジミン共演！\r\nもしもあのときに戻れるならー\r\n私の人生たった一度の“if”\n◇番組内容    \n結婚５年目ともなれば、日常生活に追われて妻も夫もなかなかお互いのことを思いやるゆとりがない。だれもが「こんなはずじゃなかった」と思い始めるころ。主人公ジュヒョクもそんな一人。職場の上司からは業績を上げろと責められ、能天気な部下に振り回される毎日。疲れて帰宅すると、今度は妻ウジンからの罵倒が待ち受けている。共稼ぎのウジンにとっては、家事や育児を押し付けて遅く帰ってくる夫が憎らしくてたまらない。\n◇出演者      \nチソン\r\nハン・ジミン\r\nチャン・スンジョ\r\nカン・ハンナ",
  "start": 1665286200000,
  "end": 1665289800000,
  "seconds": 3600,
  "description": "チソン×ハン・ジミン共演！\r\nもしもあのときに戻れるならー\r\n私の人生たった一度の“if”",
  "extra": {
    "番組内容    ": "結婚５年目ともなれば、日常生活に追われて妻も夫もなかなかお互いのことを思いやるゆとりがない。だれもが「こんなはずじゃなかった」と思い始めるころ。主人公ジュヒョクもそんな一人。職場の上司からは業績を上げろと責められ、能天気な部下に振り回される毎日。疲れて帰宅すると、今度は妻ウジンからの罵倒が待ち受けている。共稼ぎのウジンにとっては、家事や育児を押し付けて遅く帰ってくる夫が憎らしくてたまらない。",
    "出演者      ": "チソン\r\nハン・ジミン\r\nチャン・スンジョ\r\nカン・ハンナ"
  },
  "channel": {
    "type": "GR",
    "channel": "30",
    "name": "チバテレ１",
    "id": "1hgokns",
    "sid": 27704,
    "nid": 32327,
    "hasLogoData": true,
    "n": 10
  },
  "subTitle": "",
  "episode": 12,
  "flags": [
    "字"
  ]
}
