{
  "id": "381xj5r1pv",
  "category": "drama",
  "title": "コンフィデンスマンＪＰ◇２８日夜は劇場版　＃０３",
  "fullTitle": "コンフィデンスマンＪＰ◇２８日夜は劇場版　＃０３🈞🈑🈖🈓",
  "detail": "標的は悪徳美術評論家（石黒賢）！大金うごめくアート界を舞台にダー子（長澤まさみ）たちが偽物の絵画で釣り上げる。果たして見破られず騙し取れるのか！",
  "start": 1734411000000,
  "end": 1734414480000,
  "seconds": 3480,
  "channel": {
    "type": "GR",
    "channel": "21",
    "name": "フジテレビ",
    "id": "1i597dt",
    "sid": 1057,
    "nid": 32740,
    "hasLogoData": true,
    "n": 30
  },
  "subTitle": "",
  "episode": 3,
  "flags": [
    "再",
    "字",
    "解",
    "デ"
  ]
}
