{
  "id": "381f5kukzl",
  "category": "information",
  "title": "未来へ１７ＡＣＴＩＯＮ☆ＴＶ「“アライ先生”を増やそう」",
  "fullTitle": "未来へ１７ＡＣＴＩＯＮ☆ＴＶ「“アライ先生”を増やそう」🈑",
  "detail": "ＬＧＢＴの子供が幸せな学校生活を送れるようにと研修に取り組んでいるのがＮＰＯ法人ＲｅＢｉｔ。トランスジェンダーの子供の半数以上が自殺を考えたこともあるという。",
  "start": 1697856120000,
  "end": 1697856840000,
  "seconds": 720,
  "channel": {
    "type": "GR",
    "channel": "27",
    "name": "ＮＨＫ総合２・東京",
    "id": "1i50mpt",
    "sid": 1025,
    "nid": 32736,
    "hasLogoData": true,
    "n": 1
  },
  "subTitle": "“アライ先生”を増やそう",
  "episode": 1,
  "flags": [
    "字"
  ]
}
