{
  "id": "381ocd81yg",
  "category": "news",
  "title": "ｎｅｗｓ　ｅｖｅｒｙ．“ボウガン”の矢撃たれ４人死傷…住人の男子学生",
  "fullTitle": "ｎｅｗｓ　ｅｖｅｒｙ．[字]“ボウガン”の矢撃たれ４人死傷…住人の男子学生「放った」",
  "detail": "「東京アラート」３日目…新規感染者２８人“夜の町”再開で見守り強化「とまどい」も▼感染発表から一夜…坂本選手らすでに陰性▼花火や祭りも続々中止…夏の風物詩ピンチ\n◇出演者\n藤井貴彦、陣内貴美子、鈴江奈々、中島芽生、ハードキャッスルエリザベス、伊藤大海、木原実、小林史、渡辺裕太\n◇番組内容\n番組ホームページ　ｈｔｔｐ：／／ｗｗｗ．ｎｔｖ．ｃｏ．ｊｐ／ｅｖｅｒｙ／\r\n\r\n※放送内容を変更する場合があります。ご了承ください。",
  "start": 1591253400000,
  "end": 1591264800000,
  "seconds": 11400,
  "description": "「東京アラート」３日目…新規感染者２８人“夜の町”再開で見守り強化「とまどい」も▼感染発表から一夜…坂本選手らすでに陰性▼花火や祭りも続々中止…夏の風物詩ピンチ",
  "extra": {
    "出演者": "藤井貴彦、陣内貴美子、鈴江奈々、中島芽生、ハードキャッスルエリザベス、伊藤大海、木原実、小林史、渡辺裕太",
    "番組内容": "番組ホームページ　ｈｔｔｐ：／／ｗｗｗ．ｎｔｖ．ｃｏ．ｊｐ／ｅｖｅｒｙ／\r\n\r\n※放送内容を変更する場合があります。ご了承ください。"
  },
  "channel": {
    "type": "GR",
    "channel": "12",
    "name": "日テレ１",
    "id": "1i54x1s",
    "sid": 1040,
    "nid": 32738,
    "hasLogoData": true,
    "n": 15
  },
  "subTitle": "放った",
  "episode": null,
  "flags": [
    "字"
  ]
}
