{
  "id": "idozwuw",
  "category": "documentary",
  "title": "流転　～沖縄　引き裂かれた集落～",
  "fullTitle": "流転　～沖縄　引き裂かれた集落～🈑",
  "detail": "沖縄県宜野湾市、かつて美しい水田が広がる集落があった。「伊佐浜」。今、そこにあるのはアメリカ軍基地だ。故郷を奪われた伊佐浜住民たちの流転の人生を見つめる。\n◇番組内容\n沖縄戦から１２年後の１９５７年、５９人の沖縄の人々＝ウチナーンチュが地球の裏側、ブラジルのサントス港に降り立った。宜野湾市にあった伊佐浜集落の人々だ。かつて美田が広がっていた集落は、アメリカ軍に強制的に接収され、基地が建設された。故郷を奪われた住民の半数は遠い異国に新天地を求め、６６年の歳月が流れた今もブラジルで暮らす人がいる。伊佐浜のウチナーンチュはどう戦後を生き抜いたのか。流転の人生を見つめる\n◇出演者\n【語り】ジョン・カビラ",
  "start": 1699524000000,
  "end": 1699526760000,
  "seconds": 2760,
  "description": "沖縄県宜野湾市、かつて美しい水田が広がる集落があった。「伊佐浜」。今、そこにあるのはアメリカ軍基地だ。故郷を奪われた伊佐浜住民たちの流転の人生を見つめる。",
  "extra": {
    "番組内容": "沖縄戦から１２年後の１９５７年、５９人の沖縄の人々＝ウチナーンチュが地球の裏側、ブラジルのサントス港に降り立った。宜野湾市にあった伊佐浜集落の人々だ。かつて美田が広がっていた集落は、アメリカ軍に強制的に接収され、基地が建設された。故郷を奪われた住民の半数は遠い異国に新天地を求め、６６年の歳月が流れた今もブラジルで暮らす人がいる。伊佐浜のウチナーンチュはどう戦後を生き抜いたのか。流転の人生を見つめる",
    "出演者": "【語り】ジョン・カビラ"
  },
  "channel": {
    "type": "BS",
    "channel": "BS15_0",
    "name": "ＮＨＫＢＳ１",
    "id": "8kpx",
    "sid": 101,
    "nid": 4,
    "hasLogoData": true,
    "n": 41
  },
  "subTitle": "伊佐浜",
  "episode": 1,
  "flags": [
    "字"
  ]
}
