{
  "id": "w66hix6",
  "category": "variety",
  "title": "めちゃ2イケてるッ！",
  "fullTitle": "めちゃ2イケてるッ！　#230　　　ちょっと懐かしい映像、貴重な映像満載！",
  "detail": "「春の期末テスト完全版 カットするのは超もったいないスペシャル」「なるほど！ザ・赤DVD」　ほか\r\n（地上波放送日　2015年4月18日）",
  "start": 1617202800000,
  "end": 1617205800000,
  "seconds": 3000,
  "channel": {
    "type": "CS",
    "channel": "CS20",
    "name": "フジテレビＯＮＥ",
    "id": "f0cz",
    "sid": 307,
    "nid": 7,
    "hasLogoData": false,
    "n": 111
  },
  "subTitle": "ちょっと懐かしい映像、貴重な映像満載！",
  "episode": 230,
  "flags": []
}
