{
  "id": "36l9gkugk6",
  "category": "variety",
  "title": "キンシオ▽植物の地名の旅",
  "fullTitle": "キンシオ▽植物の地名の旅",
  "detail": "キン・シオタニが行きたいところに行き、知りたいことを知る３０分。\n◇番組内容\nキンシオの「植物の地名の旅」。今週は東京都大田区蒲田からスタート！駅前にはアーケード商店街がたくさん！天気予報は雨だが濡れる心配がなくて喜ぶキンシオ。蒲田駅から京急蒲田駅まで歩いてみるといろいろな発見が！江戸時代から続く蒲田の歴史に感動。新旧が入り混じりどこか懐かしい街、蒲田の旅の結末は！？\r\n\n◇出演者\nキン・シオタニ、立川晴の輔",
  "start": 1600011000000,
  "end": 1600012800000,
  "seconds": 1800,
  "description": "キン・シオタニが行きたいところに行き、知りたいことを知る３０分。",
  "extra": {
    "番組内容": "キンシオの「植物の地名の旅」。今週は東京都大田区蒲田からスタート！駅前にはアーケード商店街がたくさん！天気予報は雨だが濡れる心配がなくて喜ぶキンシオ。蒲田駅から京急蒲田駅まで歩いてみるといろいろな発見が！江戸時代から続く蒲田の歴史に感動。新旧が入り混じりどこか懐かしい街、蒲田の旅の結末は！？\r\n",
    "出演者": "キン・シオタニ、立川晴の輔\r\n"
  },
  "channel": {
    "type": "GR",
    "channel": "17",
    "name": "チバテレ１",
    "id": "1hgokns",
    "sid": 27704,
    "nid": 32327,
    "hasLogoData": true,
    "n": 9
  },
  "subTitle": "",
  "episode": null,
  "flags": []
}
