{
  "id": "36tfa8ghcx",
  "category": "anime",
  "title": "アイカツ！",
  "fullTitle": "アイカツ！　＃４６「リスペクトＪ☆」",
  "detail": "私のアツいアイドル活動！『アイカツ！』始まりますっ！\n◇あらすじ◇\nスターライト学園のトップアイドルを決めるスターライトクイーンカップの開催が決定！いちごたちは美月に追いつくため、美月の“空白の一年間”について調べることに。すると、驚くべき事実が発覚して…！\n◇出演者\n【星宮いちご】諸星すみれ\r\n【霧矢あおい】田所あずさ\r\n【紫吹 蘭】大橋彩香\r\n【神崎美月】寿美菜子\r\n【星宮りんご】能登麻美子\r\n【星宮らいち】瀬戸麻沙美\r\n【光石織姫】松谷彼哉\r\n【ジョニー別府】保村 真",
  "start": 1582797600000,
  "end": 1582799400000,
  "seconds": 1800,
  "description": "私のアツいアイドル活動！『アイカツ！』始まりますっ！",
  "extra": {
    "あらすじ◇": "スターライト学園のトップアイドルを決めるスターライトクイーンカップの開催が決定！いちごたちは美月に追いつくため、美月の“空白の一年間”について調べることに。すると、驚くべき事実が発覚して…！",
    "出演者": "【星宮いちご】諸星すみれ\r\n【霧矢あおい】田所あずさ\r\n【紫吹 蘭】大橋彩香\r\n【神崎美月】寿美菜子\r\n【星宮りんご】能登麻美子\r\n【星宮らいち】瀬戸麻沙美\r\n【光石織姫】松谷彼哉\r\n【ジョニー別府】保村 真"
  },
  "channel": {
    "type": "GR",
    "channel": "3",
    "name": "ＴＯＫＹＯ　ＭＸ１",
    "id": "1hkhnrs",
    "sid": 23608,
    "nid": 32391,
    "hasLogoData": true,
    "n": 32
  },
  "subTitle": "リスペクトＪ☆",
  "episode": 46,
  "flags": []
}
