{
  "id": "idtrbu3",
  "category": "drama",
  "title": "＜サスペンス劇場＞潔癖クンの殺人ファイル３　事件はワイドショーから始まった",
  "fullTitle": "🈑＜サスペンス劇場＞潔癖クンの殺人ファイル３　事件はワイドショーから始まった",
  "detail": "坂上忍の刑事ドラマ初主演のサスペンスシリーズ。坂上＆温水洋一の息の合った掛け合いに注目。ゲストの渡辺直美を見て速水刑事（温水）が涙ぐむシーンも！？",
  "start": 1711594800000,
  "end": 1711602000000,
  "seconds": 7200,
  "channel": {
    "type": "BS",
    "channel": "BS13_1",
    "name": "ＢＳフジ・１８１",
    "id": "8ks5",
    "sid": 181,
    "nid": 4,
    "hasLogoData": true,
    "n": 57
  },
  "subTitle": "",
  "episode": 1,
  "flags": [
    "字"
  ]
}
