{
  "id": "36l9gkufht",
  "category": "variety",
  "title": "いいね！信州スゴヂカラ▽今からが旬！八ヶ岳の夏にはイチゴがある！",
  "fullTitle": "いいね！信州スゴヂカラ▽今からが旬！八ヶ岳の夏にはイチゴがある！🈑",
  "detail": "八ヶ岳山麓で栽培されるジューシーで香り高い「夏イチゴ」が今、注目を集めています。標高１０００ｍの富士見町で奮闘する若手農家に密着し、夏イチゴの魅力に迫ります。\n◇番組内容\n八ヶ岳の夏イチゴ栽培を牽引する、夏イチゴ専門個人農家「高原のエコーズ」代表の鈴木慎吾さんに密着。５月～１２月が旬の、ジューシーで香り高い「夏イチゴ」の魅力に迫ります。栽培方法はもちろん、収穫・梱包・発送方法にまで光る鈴木さんのこだわり。業界関係者からも熱い視線が注がれます。先輩夏イチゴ農家と開発した、絶品デザートもご紹介。瑞々しい新緑の八ヶ岳山麓から、夏イチゴの魅力をたっぷりとお届けします。\n◇出演者\nナレーション：楠原由祐子",
  "start": 1654934400000,
  "end": 1654936200000,
  "seconds": 1800,
  "description": "八ヶ岳山麓で栽培されるジューシーで香り高い「夏イチゴ」が今、注目を集めています。標高１０００ｍの富士見町で奮闘する若手農家に密着し、夏イチゴの魅力に迫ります。",
  "extra": {
    "番組内容": "八ヶ岳の夏イチゴ栽培を牽引する、夏イチゴ専門個人農家「高原のエコーズ」代表の鈴木慎吾さんに密着。５月～１２月が旬の、ジューシーで香り高い「夏イチゴ」の魅力に迫ります。栽培方法はもちろん、収穫・梱包・発送方法にまで光る鈴木さんのこだわり。業界関係者からも熱い視線が注がれます。先輩夏イチゴ農家と開発した、絶品デザートもご紹介。瑞々しい新緑の八ヶ岳山麓から、夏イチゴの魅力をたっぷりとお届けします。",
    "出演者": "ナレーション：楠原由祐子"
  },
  "channel": {
    "type": "GR",
    "channel": "30",
    "name": "チバテレ１",
    "id": "1hgokns",
    "sid": 27704,
    "nid": 32327,
    "hasLogoData": true,
    "n": 9
  },
  "subTitle": "夏イチゴ",
  "episode": 1,
  "flags": [
    "字"
  ]
}
