{
  "id": "381ocd84wp",
  "category": "drama",
  "title": "パンドラの果実　～科学犯罪捜査ファイル～#08",
  "fullTitle": "パンドラの果実　～科学犯罪捜査ファイル～#08🈖🈑🈓",
  "detail": "最終章！8話は妻そっくりの遺体!?ディーン・フジオカ主演！岸井ゆきの、ユースケ・サンタマリアが最先端科学が起こす怪事件の真相に挑む、新時代サイエンスミステリー！\n◇出演者\nディーン・フジオカ　岸井ゆきの\r\n佐藤隆太 西村和彦　本仮屋ユイカ　安藤政信\r\n板尾創路　石野真子\r\n加藤雅也／ユースケ・サンタマリア\r\n\r\n【第8話ゲスト】\r\n鷲見玲奈　岡 宏明\r\n\r\n栗山千明　平山祐介\n◇番組内容\n■小比類巻の妻・亜美（本仮屋）そっくりの遺体が！　全身の血液が失われた女性の遺体。亜美の衝撃の秘密が明かされ、小比類巻（ディーン）は激しく動揺する！！\r\n■消滅したはずのプロメテウス・ウイルスが存在していることが分かり…！？そして、最強の遺伝子・エルマー遺伝子とは！？歴史を変える大発見に驚愕する最上（岸井）\r\n■榊原（加藤）の真の目的が明らかに！32年前の“悪魔の子事件”とは？小比類巻の娘に危機が!?\n◇監督・演出\n監督：羽住英一郎\n◇原作・脚本\n原作：中村 啓「SCIS　科学犯罪捜査班　天才科学者・最上友紀子の挑戦」(光文社文庫)\r\n\r\n脚本：福田哲平　関 久代\n◇音楽\n音楽：菅野祐悟\r\n主題歌：「Apple」　DEAN FUJIOKA\r\n　　　　　　(A-Sketch)\n◇制作\nチーフプロデューサー：三上絵里子　茶ノ前 香\r\nプロデューサー：能勢荘志　尾上貴洋　古屋 厚\r\n\r\n制作協力：ロボット\r\n製作著作：日本テレビ　HJホールディングス",
  "start": 1654952400000,
  "end": 1654955640000,
  "seconds": 3240,
  "description": "最終章！8話は妻そっくりの遺体!?ディーン・フジオカ主演！岸井ゆきの、ユースケ・サンタマリアが最先端科学が起こす怪事件の真相に挑む、新時代サイエンスミステリー！",
  "extra": {
    "出演者": "ディーン・フジオカ　岸井ゆきの\r\n佐藤隆太 西村和彦　本仮屋ユイカ　安藤政信\r\n板尾創路　石野真子\r\n加藤雅也／ユースケ・サンタマリア\r\n\r\n【第8話ゲスト】\r\n鷲見玲奈　岡 宏明\r\n\r\n栗山千明　平山祐介",
    "番組内容": "■小比類巻の妻・亜美（本仮屋）そっくりの遺体が！　全身の血液が失われた女性の遺体。亜美の衝撃の秘密が明かされ、小比類巻（ディーン）は激しく動揺する！！\r\n■消滅したはずのプロメテウス・ウイルスが存在していることが分かり…！？そして、最強の遺伝子・エルマー遺伝子とは！？歴史を変える大発見に驚愕する最上（岸井）\r\n■榊原（加藤）の真の目的が明らかに！32年前の“悪魔の子事件”とは？小比類巻の娘に危機が!?",
    "監督・演出": "監督：羽住英一郎",
    "原作・脚本": "原作：中村 啓「SCIS　科学犯罪捜査班　天才科学者・最上友紀子の挑戦」(光文社文庫)\r\n\r\n脚本：福田哲平　関 久代",
    "音楽": "音楽：菅野祐悟\r\n主題歌：「Apple」　DEAN FUJIOKA\r\n　　　　　　(A-Sketch)",
    "制作": "チーフプロデューサー：三上絵里子　茶ノ前 香\r\nプロデューサー：能勢荘志　尾上貴洋　古屋 厚\r\n\r\n制作協力：ロボット\r\n製作著作：日本テレビ　HJホールディングス"
  },
  "channel": {
    "type": "GR",
    "channel": "25",
    "name": "日テレ１",
    "id": "1i54x1s",
    "sid": 1040,
    "nid": 32738,
    "hasLogoData": true,
    "n": 16
  },
  "subTitle": "",
  "episode": 8,
  "flags": [
    "解",
    "字",
    "デ"
  ]
}
