{
  "id": "381sxri0li",
  "category": "information",
  "title": "アッコにおまかせ！【ジャニーズ性加害問題 会見を総まとめ▼所属タレントに影響も】",
  "fullTitle": "アッコにおまかせ！【ジャニーズ性加害問題 会見を総まとめ▼所属タレントに影響も】",
  "detail": "▼新社長に東山紀之(56)就任…年内で芸能界引退へ▼会見を見た被害者や所属タレントも続々コメント発表…その内容は？▼東山新社長過去にハラスメント疑惑？記者が追及",
  "start": 1694313900000,
  "end": 1694318400000,
  "seconds": 4500,
  "channel": {
    "type": "GR",
    "channel": "22",
    "name": "ＴＢＳ２",
    "id": "1i5727t",
    "sid": 1049,
    "nid": 32739,
    "hasLogoData": true,
    "n": 25
  },
  "subTitle": "ジャニーズ性加害問題 会見を総まとめ▼所属タレントに影響も",
  "episode": 1,
  "flags": []
}
