{
  "id": "w68ip0c",
  "category": "documentary",
  "title": "テキサスWILDパトロール！S5特別編：東テキサスのヒーローたち",
  "fullTitle": "テキサスWILDパトロール！S5特別編：東テキサスのヒーローたち(字)",
  "detail": "テキサス東部で活躍する猟区管理官たちに密着する特別編。違法なハンターを取り締まるためにシカのおとりを設置。民家の近くにいたアリゲーターを追い払う。",
  "start": 1638840600000,
  "end": 1638844200000,
  "seconds": 3600,
  "channel": {
    "type": "CS",
    "channel": "CS6",
    "name": "アニマルプラネット",
    "id": "f0dx",
    "sid": 341,
    "nid": 7,
    "hasLogoData": true,
    "n": 133
  },
  "subTitle": "",
  "episode": null,
  "flags": [
    "字"
  ]
}
