{
  "id": "381sxrg7jd",
  "category": "sports",
  "title": "ＣＲＯＳＳ　ＬＩＮＥ～アスリート×東北　みらいを創る～",
  "fullTitle": "ＣＲＯＳＳ　ＬＩＮＥ～アスリート×東北　みらいを創る～[解][字]",
  "detail": "★ナレーション大友康平★釜石出身パラ水泳村田奈々選手と岩手で１２０年以上の歴史を持つ南部潜りの潜水士・磯崎元勝さんが「水との出会い」を語り合う\n◇番組内容\n★パラ水泳村田奈々選手★岩手県釜石市出身★高校１年の時事故で車いす生活に★知人の紹介で水泳を始め瞬く間に日本のトップクラスへと成長★岩手県で１２０年以上の歴史を持つ「南部潜り」の潜水士・磯崎元勝さん６０歳★震災後１か月で漁を再開・被災地の希望となった★現在後継者を求め地元の学生を指導\r\n\n◇出演者\n★ナレーション大友康平★村田奈々選手★磯崎元勝さん\r\n\n◇次回\n★４月８日（水）よる１０：５７～★釜石出身パラ水泳・村田奈々選手と岩手「南部潜り」の潜水士・磯崎元勝さんが「復興」を語る\r\n\n◇公式ページ\n◇番組ＨＰ http://www.tbs.co.jp/cross-line/\r\n\n◇おことわり\n番組の内容と放送時間は変更になる可能性があります。",
  "start": 1585749420000,
  "end": 1585749600000,
  "seconds": 180,
  "description": "★ナレーション大友康平★釜石出身パラ水泳村田奈々選手と岩手で１２０年以上の歴史を持つ南部潜りの潜水士・磯崎元勝さんが「水との出会い」を語り合う",
  "extra": {
    "番組内容": "★パラ水泳村田奈々選手★岩手県釜石市出身★高校１年の時事故で車いす生活に★知人の紹介で水泳を始め瞬く間に日本のトップクラスへと成長★岩手県で１２０年以上の歴史を持つ「南部潜り」の潜水士・磯崎元勝さん６０歳★震災後１か月で漁を再開・被災地の希望となった★現在後継者を求め地元の学生を指導\r\n",
    "出演者": "★ナレーション大友康平★村田奈々選手★磯崎元勝さん\r\n",
    "次回": "★４月８日（水）よる１０：５７～★釜石出身パラ水泳・村田奈々選手と岩手「南部潜り」の潜水士・磯崎元勝さんが「復興」を語る\r\n",
    "公式ページ": "◇番組ＨＰ http://www.tbs.co.jp/cross-line/\r\n",
    "おことわり": "番組の内容と放送時間は変更になる可能性があります。\r\n"
  },
  "channel": {
    "type": "GR",
    "channel": "9",
    "name": "ＴＢＳ１",
    "id": "1i5727s",
    "sid": 1048,
    "nid": 32739,
    "hasLogoData": true,
    "n": 22
  },
  "subTitle": "水との出会い",
  "episode": null,
  "flags": [
    "解",
    "字"
  ]
}
