{
  "id": "381jqz0kke",
  "category": "music",
  "title": "みんなのうた「パプリカ　米津玄師バージョン」",
  "fullTitle": "みんなのうた「パプリカ　米津玄師バージョン」「Ｉ．ｍ．（アイム）」",
  "detail": "▽「パプリカ　米津玄師バージョン」うた：米津玄師／▽「Ｉ．ｍ．（アイム）」うた：ロザリーナ\n◇番組内容\n▽「パプリカ　米津玄師バージョン」うた：米津玄師／▽「Ｉ．ｍ．（アイム）」うた：ロザリーナ",
  "start": 1568617200000,
  "end": 1568617500000,
  "seconds": 300,
  "description": "▽「パプリカ　米津玄師バージョン」うた：米津玄師／▽「Ｉ．ｍ．（アイム）」うた：ロザリーナ",
  "extra": {
    "番組内容": "▽「パプリカ　米津玄師バージョン」うた：米津玄師／▽「Ｉ．ｍ．（アイム）」うた：ロザリーナ"
  },
  "channel": {
    "type": "GR",
    "channel": "26",
    "name": "ＮＨＫＥテレ１東京",
    "id": "1i52rvs",
    "sid": 1032,
    "nid": 32737,
    "hasLogoData": true,
    "n": 2
  },
  "subTitle": "Ｉ．ｍ．（アイム）",
  "episode": null,
  "flags": []
}
