{
  "id": "381ocd7wsl",
  "category": "variety",
  "title": "ニノさん▼堤真一とオススメ日帰りキャンプ▽首と腰が痛いVSゴッドハンド凄技",
  "fullTitle": "ニノさん▼堤真一とオススメ日帰りキャンプ▽首と腰が痛いVSゴッドハンド凄技🈑",
  "detail": "キャンプ好きの堤真一に家族で楽しめるキャンプ場＆寄り道スポットご紹介▽ブラックジャック熱戦！堤とまーちゃんが風磨を4の字固め!?▽ゴッドハンド整体師にニノ釘付け\n◇出演者\n【ＭＣ】二宮和也\r\n【メンバー】菊池風磨（timelesz）・陣内智則・ガンバレルーヤ\r\n【ゲスト】堤真一\r\n【ＶＴＲ】宮下草薙\n◇番組内容\n「真くん、飯食いに行かない？」ニノから堤真一への誘い…ニノの㊙関係性！▽キャンプ特集を宮下草薙が大調査！四季を感じながら天然氷のかき氷＆川遊びにマス釣り体験＆自然に囲まれた日帰り温泉も！▽首と腰が痛い…堤が神業整体師の施術を体験＆ニノも陣も興味津々で…！▽今回も大盛り上がりのブラックジャック！暑い日に食べたいもの＆ジェネレーションギャップで驚く言葉…風磨ガンバレのバトルに堤もまさかの参戦で大騒ぎ！\n◇制作\n【プロデューサー】國谷茉莉\r\n【演出】石崎史郎",
  "start": 1724549100000,
  "end": 1724552700000,
  "seconds": 3600,
  "description": "キャンプ好きの堤真一に家族で楽しめるキャンプ場＆寄り道スポットご紹介▽ブラックジャック熱戦！堤とまーちゃんが風磨を4の字固め!?▽ゴッドハンド整体師にニノ釘付け",
  "extra": {
    "出演者": "【ＭＣ】二宮和也\r\n【メンバー】菊池風磨（timelesz）・陣内智則・ガンバレルーヤ\r\n【ゲスト】堤真一\r\n【ＶＴＲ】宮下草薙",
    "番組内容": "「真くん、飯食いに行かない？」ニノから堤真一への誘い…ニノの㊙関係性！▽キャンプ特集を宮下草薙が大調査！四季を感じながら天然氷のかき氷＆川遊びにマス釣り体験＆自然に囲まれた日帰り温泉も！▽首と腰が痛い…堤が神業整体師の施術を体験＆ニノも陣も興味津々で…！▽今回も大盛り上がりのブラックジャック！暑い日に食べたいもの＆ジェネレーションギャップで驚く言葉…風磨ガンバレのバトルに堤もまさかの参戦で大騒ぎ！",
    "制作": "【プロデューサー】國谷茉莉\r\n【演出】石崎史郎"
  },
  "channel": {
    "type": "GR",
    "channel": "25",
    "name": "日テレ１",
    "id": "1i54x1s",
    "sid": 1040,
    "nid": 32738,
    "hasLogoData": true,
    "n": 16
  },
  "subTitle": "",
  "episode": 1,
  "flags": [
    "字"
  ]
}
