{
  "id": "idozlx8",
  "category": "documentary",
  "title": "プロフェッショナル　仕事の流儀▽言葉の海で、心を編む～辞書編さん者・飯間浩明",
  "fullTitle": "プロフェッショナル　仕事の流儀▽言葉の海で、心を編む～辞書編さん者・飯間浩明🈖🈑",
  "detail": "“言葉ハンター”の異名を取る気鋭の辞書編纂（さん）者。街なか、ＳＮＳ…日々生まれる言葉を集め、その意味や解釈を辞書に編む。国語辞典の改訂に向けた熱き闘い！",
  "start": 1708185600000,
  "end": 1708188360000,
  "seconds": 2760,
  "channel": {
    "type": "BS",
    "channel": "BS15_0",
    "name": "ＮＨＫ　ＢＳ",
    "id": "8kpx",
    "sid": 101,
    "nid": 4,
    "hasLogoData": true,
    "n": 41
  },
  "subTitle": "",
  "episode": 1,
  "flags": [
    "解",
    "字"
  ]
}
