{
  "id": "36l9gkve89",
  "category": "drama",
  "title": "くろねこルーシー",
  "fullTitle": "くろねこルーシー[再]",
  "detail": "【サブタイトル】先人は言う。下駄の鼻緒が切れたらなんたら……\n◇番組内容\n【あらすじ】陽（山本耕史）は七回忌を終えた実家からの帰り道、リストラを宣告された。　\r\nさらには、母、幸子（鷲尾真知子）から押し付けられた二匹の黒猫の赤ちゃんを仕方なく預かることになってしまった。　\r\n鳴きやまない子猫たちに、牛乳や猫缶を差し出すが全く口にしない。　\r\n幸子に子猫を返そうと何度も電話をかけるが、呑気な声で留守電メッセージが流れるばかり。　\r\n翌日、子猫の育て方が分からず、困り果てた陽は動物病院へ。　\r\n女医の白藤からは、「赤ちゃん\n◇出演者\n【キャスト】山本耕史、京野ことみ、塚地武雅、川上麻衣子、小宮孝泰、渡辺真起子、相島一之、鷲尾真知子\r\n\n◇おしらせ\nオフィシャルサイト：ｈｔｔｐ：／／ｋｕｒｏｎｅｋｏ－ｌｕｃｙ．ｉｎｆｏ／",
  "start": 1569600000000,
  "end": 1569601800000,
  "seconds": 1800,
  "description": "【サブタイトル】先人は言う。下駄の鼻緒が切れたらなんたら……",
  "extra": {
    "番組内容": "【あらすじ】陽（山本耕史）は七回忌を終えた実家からの帰り道、リストラを宣告された。　\r\nさらには、母、幸子（鷲尾真知子）から押し付けられた二匹の黒猫の赤ちゃんを仕方なく預かることになってしまった。　\r\n鳴きやまない子猫たちに、牛乳や猫缶を差し出すが全く口にしない。　\r\n幸子に子猫を返そうと何度も電話をかけるが、呑気な声で留守電メッセージが流れるばかり。　\r\n翌日、子猫の育て方が分からず、困り果てた陽は動物病院へ。　\r\n女医の白藤からは、「赤ちゃん",
    "出演者": "【キャスト】山本耕史、京野ことみ、塚地武雅、川上麻衣子、小宮孝泰、渡辺真起子、相島一之、鷲尾真知子\r\n",
    "おしらせ": "オフィシャルサイト：ｈｔｔｐ：／／ｋｕｒｏｎｅｋｏ－ｌｕｃｙ．ｉｎｆｏ／\r\n"
  },
  "channel": {
    "type": "GR",
    "channel": "17",
    "name": "チバテレ１",
    "id": "1hgokns",
    "sid": 27704,
    "nid": 32327,
    "hasLogoData": false,
    "n": 9
  },
  "subTitle": "サブタイトル",
  "episode": null,
  "flags": [
    "再"
  ]
}
