{
  "id": "381ocd7uzp",
  "category": "sports",
  "title": "★ＳＡＰＰＯＲＯスポーツスペシャル　第９９回箱根駅伝予選会",
  "fullTitle": "★ＳＡＰＰＯＲＯスポーツスペシャル　第９９回箱根駅伝予選会🈑🈓",
  "detail": "「１秒」にかける秋の激戦！切符はわずか１０枚…夢の箱根駅伝出場をめざす過酷な「予選会」▽早稲田・明治・東海などの名門は？新鋭の初出場は？運命の結果発表まで生中継\n◇出演者\n【解説】渡辺康幸（早稲田大ＯＢ・住友電工陸上部監督）\r\n【ゲスト解説】藤原正和（中央大ＯＢ・中央大学陸上部駅伝監督）\r\n【実況】安藤翔・菅谷大介\r\n【リポート・インタビュー】森圭介・徳島えりか・弘竜太郎\n◇番組内容\nハーフマラソンを走り上位１０校が箱根駅伝へ！【出場４３校】東海／神奈川／早稲田／明治／国士舘／中央学院／日体大／山梨学院／駿河台／専修／拓殖／大東文化／筑波／上武／城西／立教／流経大／東農大／慶應義塾／東京経済／日大／亜細亜／日本薬科／武蔵野学院／芝浦工大／育英／関東学院／麗澤／桜美林／明治学院／立正／平成国際／湘南工科／東大／一橋／帝京平成／東大院／東京工大／高崎経大／東京理科／清和／成蹊／埼玉",
  "start": 1665793500000,
  "end": 1665800700000,
  "seconds": 7200,
  "description": "「１秒」にかける秋の激戦！切符はわずか１０枚…夢の箱根駅伝出場をめざす過酷な「予選会」▽早稲田・明治・東海などの名門は？新鋭の初出場は？運命の結果発表まで生中継",
  "extra": {
    "出演者": "【解説】渡辺康幸（早稲田大ＯＢ・住友電工陸上部監督）\r\n【ゲスト解説】藤原正和（中央大ＯＢ・中央大学陸上部駅伝監督）\r\n【実況】安藤翔・菅谷大介\r\n【リポート・インタビュー】森圭介・徳島えりか・弘竜太郎",
    "番組内容": "ハーフマラソンを走り上位１０校が箱根駅伝へ！【出場４３校】東海／神奈川／早稲田／明治／国士舘／中央学院／日体大／山梨学院／駿河台／専修／拓殖／大東文化／筑波／上武／城西／立教／流経大／東農大／慶應義塾／東京経済／日大／亜細亜／日本薬科／武蔵野学院／芝浦工大／育英／関東学院／麗澤／桜美林／明治学院／立正／平成国際／湘南工科／東大／一橋／帝京平成／東大院／東京工大／高崎経大／東京理科／清和／成蹊／埼玉"
  },
  "channel": {
    "type": "GR",
    "channel": "25",
    "name": "日テレ１",
    "id": "1i54x1s",
    "sid": 1040,
    "nid": 32738,
    "hasLogoData": true,
    "n": 17
  },
  "subTitle": "",
  "episode": 99,
  "flags": [
    "字",
    "デ"
  ]
}
