{
  "id": "36tfa8gdeb",
  "category": "anime",
  "title": "まじっく快斗１４１２　＃１２「聖夜・二人の怪盗ＫＩＤ」",
  "fullTitle": "まじっく快斗１４１２　＃１２「聖夜・二人の怪盗ＫＩＤ」",
  "detail": "◇あらすじ◇\n怪盗キッドが現れなくなって3ヶ月が経過。犯行の間隔がこれほど空いた事はなく、中森警部はこれには何かワケがあると深読みする。実はビッグジュエルの情報を集めている寺井がぎっくり腰になり、快斗は活動ができなかったのだ。寺井のぎっくり腰は治ったが、今は快斗の期末テストの最中。おまけに快斗は風邪も引いていた。その頃、テレビで怪盗キッドから予告状が届いたというニュースが報じられる。\n◇出演者\n【黒羽快斗(怪盗キッド)】山口勝平\r\n【中森青子】M・A・O\r\n【寺井黄之助】羽佐間道夫\r\n【小泉紅子】喜多村英梨\r\n【白馬探】宮野真守\r\n【中森銀三】石塚運昇\r\n【黒羽盗一】池田秀一",
  "start": 1711469100000,
  "end": 1711470900000,
  "seconds": 1800,
  "description": " ",
  "extra": {
    "あらすじ◇": "怪盗キッドが現れなくなって3ヶ月が経過。犯行の間隔がこれほど空いた事はなく、中森警部はこれには何かワケがあると深読みする。実はビッグジュエルの情報を集めている寺井がぎっくり腰になり、快斗は活動ができなかったのだ。寺井のぎっくり腰は治ったが、今は快斗の期末テストの最中。おまけに快斗は風邪も引いていた。その頃、テレビで怪盗キッドから予告状が届いたというニュースが報じられる。",
    "出演者": "【黒羽快斗(怪盗キッド)】山口勝平\r\n【中森青子】M・A・O\r\n【寺井黄之助】羽佐間道夫\r\n【小泉紅子】喜多村英梨\r\n【白馬探】宮野真守\r\n【中森銀三】石塚運昇\r\n【黒羽盗一】池田秀一"
  },
  "channel": {
    "type": "GR",
    "channel": "16",
    "name": "ＴＯＫＹＯ　ＭＸ１",
    "id": "1hkhnrs",
    "sid": 23608,
    "nid": 32391,
    "hasLogoData": true,
    "n": 34
  },
  "subTitle": "聖夜・二人の怪盗ＫＩＤ",
  "episode": 12,
  "flags": []
}
