{
  "id": "idozbvd",
  "category": "documentary",
  "title": "シリーズ　人体・特別版万病撃退！“腸”が免疫の鍵だった",
  "fullTitle": "シリーズ　人体・特別版（４）万病撃退！“腸”が免疫の鍵だった[SS][字][再]",
  "detail": "未公開のシーンも加えて再登場のシリーズ「人体」。消化・吸収の要である“腸”は、私たちを万病から守る全身の「免疫力」をつかさどっていることが明らかに。",
  "start": 1626393600000,
  "end": 1626396600000,
  "seconds": 3000,
  "channel": {
    "type": "BS",
    "channel": "BS15_0",
    "name": "ＮＨＫＢＳ１",
    "id": "8kpx",
    "sid": 101,
    "nid": 4,
    "hasLogoData": false,
    "n": 40
  },
  "subTitle": "",
  "episode": 4,
  "flags": [
    "SS",
    "字",
    "再"
  ]
}
