{
  "id": "idrytt6",
  "category": "information",
  "title": "ウチ、“断捨離”しました！　「史上最大級の物量　古民家から父と娘がSOS」後編",
  "fullTitle": "🈑ウチ、“断捨離”しました！　「史上最大級の物量　古民家から父と娘がSOS」後編",
  "detail": "築250年以上の古民家に、たった1人で住んでいる高齢の父親。捨てるものなどない、今のままで幸せと言い張る。孫も加わり、番組史上最大級の物量の家が大変化なるか!?",
  "start": 1696939200000,
  "end": 1696942800000,
  "seconds": 3600,
  "channel": {
    "type": "BS",
    "channel": "BS01_3",
    "name": "ＢＳ朝日１",
    "id": "8krb",
    "sid": 151,
    "nid": 4,
    "hasLogoData": true,
    "n": 48
  },
  "subTitle": "史上最大級の物量　古民家から父と娘がSOS",
  "episode": 1,
  "flags": [
    "字"
  ]
}
