{
  "id": "idozo49",
  "category": "documentary",
  "title": "スポーツ×ヒューマン　頂点を突け　その強き剣で～フェンシング・加納虹輝～",
  "fullTitle": "スポーツ×ヒューマン　頂点を突け　その強き剣で～フェンシング・加納虹輝～🈑",
  "detail": "フェンシング日本代表の加納虹輝。東京五輪ではエペ団体で金を獲得し、去年は世界ランキング１位にもなった。パリ五輪で狙うのは個人戦の金メダル！戦いの日々に密着した。\n◇番組内容\nリーチの長い選手が有利とされるフェンシング。加納は身長１７３センチとトップ選手としては小柄だ。卓越した剣さばきと圧倒的なスピードで、ライバルを倒してきた。得意技は矢のように飛び込む「フレッシュ」。世界屈指の速さを誇る。昨秋、パリ五輪に向けた大事なシーズンが開幕した。ところが相手選手は加納のスピードを警戒していた。繰り出したフレッシュも交わされてしまう。加納は戦い方を見直すことを求められる。",
  "start": 1708696200000,
  "end": 1708698900000,
  "seconds": 2700,
  "description": "フェンシング日本代表の加納虹輝。東京五輪ではエペ団体で金を獲得し、去年は世界ランキング１位にもなった。パリ五輪で狙うのは個人戦の金メダル！戦いの日々に密着した。",
  "extra": {
    "番組内容": "リーチの長い選手が有利とされるフェンシング。加納は身長１７３センチとトップ選手としては小柄だ。卓越した剣さばきと圧倒的なスピードで、ライバルを倒してきた。得意技は矢のように飛び込む「フレッシュ」。世界屈指の速さを誇る。昨秋、パリ五輪に向けた大事なシーズンが開幕した。ところが相手選手は加納のスピードを警戒していた。繰り出したフレッシュも交わされてしまう。加納は戦い方を見直すことを求められる。"
  },
  "channel": {
    "type": "BS",
    "channel": "BS15_0",
    "name": "ＮＨＫ　ＢＳ",
    "id": "8kpx",
    "sid": 101,
    "nid": 4,
    "hasLogoData": true,
    "n": 41
  },
  "subTitle": "",
  "episode": 1,
  "flags": [
    "字"
  ]
}
