{
  "id": "381jqz29f6",
  "category": "documentary",
  "title": "ＮＨＫ短歌　題「前・後」",
  "fullTitle": "ＮＨＫ短歌　題「前・後」🈑",
  "detail": "選者：大森静佳、ゲスト：伊藤亜紗（美学者）。題「前・後」。伊藤さんが研究している美学とは？改作コーナーでは、比喩の使い方のポイントを解説。司会：有森也実",
  "start": 1647928800000,
  "end": 1647930300000,
  "seconds": 1500,
  "channel": {
    "type": "GR",
    "channel": "26",
    "name": "ＮＨＫＥテレ２東京",
    "id": "1i52rvt",
    "sid": 1033,
    "nid": 32737,
    "hasLogoData": true,
    "n": 3
  },
  "subTitle": "前・後",
  "episode": 1,
  "flags": [
    "字"
  ]
}
