{
  "id": "idymv0a",
  "category": "drama",
  "title": "韓ドラ「ホテルデルーナ～月明かりの恋人～」　＃６",
  "fullTitle": "韓ドラ「ホテルデルーナ～月明かりの恋人～」　＃６",
  "detail": "マンウォルは真っ向から向かってくるチャンソンに調子を崩されている中、女性の霊のために人捜しを手伝うチャンソンだが、マンウォルは何かが腑に落ちない様子で…？",
  "start": 1665741600000,
  "end": 1665745080000,
  "seconds": 3480,
  "channel": {
    "type": "BS",
    "channel": "BS23_2",
    "name": "ＢＳＪａｐａｎｅｘｔ",
    "id": "8kuf",
    "sid": 263,
    "nid": 4,
    "hasLogoData": true,
    "n": 82
  },
  "subTitle": "ホテルデルーナ～月明かりの恋人～",
  "episode": 6,
  "flags": []
}
