{
  "id": "381f5kuzlk",
  "category": "drama",
  "title": "【特選！時代劇】伝七捕物帳（３）夫婦道（めおとみち）、江戸女房の心意気",
  "fullTitle": "【特選！時代劇】伝七捕物帳（３）夫婦道（めおとみち）、江戸女房の心意気🈖🈑",
  "detail": "岡場所で行き倒れが出て伝七（中村梅雀）たちが駆けつける。遺体の腹には殴られた跡があるが、同心秋月（川野太郎）は行き倒れと決めつけて処理する。不審に思った伝七は…",
  "start": 1665868200000,
  "end": 1665870780000,
  "seconds": 2580,
  "channel": {
    "type": "GR",
    "channel": "27",
    "name": "ＮＨＫ総合２・東京",
    "id": "1i50mpt",
    "sid": 1025,
    "nid": 32736,
    "hasLogoData": true,
    "n": 1
  },
  "subTitle": "",
  "episode": 3,
  "flags": [
    "解",
    "字"
  ]
}
