{
  "id": "381ocda4gf",
  "category": "variety",
  "title": "日テレ＋「明日のしゃべくり007”憑依ものまね芸人SＰ”を一部先行公開‼」",
  "fullTitle": "日テレ＋「明日のしゃべくり007”憑依ものまね芸人SＰ”を一部先行公開‼」🈑",
  "detail": "ものまねを超えた憑依芸で話題‼松本人志完コピＪＰvs”素の志村けん”ものまね芸人が参戦‼▽超恋愛体質ＪＰの初恋秘話…初恋女性と20年ぶりの再会へ",
  "start": 1684068840000,
  "end": 1684069200000,
  "seconds": 360,
  "channel": {
    "type": "GR",
    "channel": "25",
    "name": "日テレ２",
    "id": "1i54x1t",
    "sid": 1041,
    "nid": 32738,
    "hasLogoData": true,
    "n": 18
  },
  "subTitle": "明日のしゃべくり007”憑依ものまね芸人SＰ”を一部先行公開‼",
  "episode": 1,
  "flags": [
    "字"
  ]
}
