{
  "id": "idp4bqz",
  "category": "documentary",
  "title": "スイーツ列車紀行　マレー半島　５ｍｉｎ．　マレーシア　世界のお菓子と技が集結！",
  "fullTitle": "スイーツ列車紀行　マレー半島　５ｍｉｎ．　マレーシア　世界のお菓子と技が集結！🈑",
  "detail": "モノレールに乗り国際都市クアラルンプールのスイーツを発掘。街角では欧州や中東、北アフリカなどの人気スイーツが大集結！世界トップクラスのあめ細工、こりゃスゴ技だ！",
  "start": 1686146100000,
  "end": 1686146400000,
  "seconds": 300,
  "channel": {
    "type": "BS",
    "channel": "BS03_1",
    "name": "ＮＨＫＢＳプレミアム",
    "id": "8kpz",
    "sid": 103,
    "nid": 4,
    "hasLogoData": true,
    "n": 43
  },
  "subTitle": "",
  "episode": 1,
  "flags": [
    "字"
  ]
}
