{
  "id": "381jqz0jx8",
  "category": "anime",
  "title": "アニメ　プラネテス",
  "fullTitle": "アニメ　プラネテス（７）「地球外少女」[字]",
  "detail": "時は２０７５年。宇宙開発が進む一方、宇宙のゴミ（デブリ）が発生し、社会問題になっていた。美しい宇宙を取り戻すことはできるのか？デブリの回収に奮闘する人々の物語。\n◇番組内容\nハチマキは全治１週間の怪我と診断され、治療のため月の病院に入院した。そこで彼は、かつて小惑星帯を初めて有人探査したベテラン航海士ハリー・ローランドの老いた姿と出会う。そしてもう一人、ノノという少女とも知り合いになる。その病院に１２年も滞在し、海に憧れをもつノノと九十九里浜生まれのハチマキはすっかり意気投合して語り合い、いっしょにカードゲームをするようになった。\n◇出演者\n【声】田中一成，雪野五月，折笠愛，こおろぎさとみ，秋元羊介，檜山修之，倉田雅世，鳥海勝美，百々麻子，三戸耕三，柳沢栄治，小林恭治\n◇原作・脚本\n【原作】幸村誠，【脚本】大河内一楼\n◇監督・演出\n【監督】谷口悟朗\n◇制作\n～サンライズ制作～",
  "start": 1645956000000,
  "end": 1645957500000,
  "seconds": 1500,
  "description": "時は２０７５年。宇宙開発が進む一方、宇宙のゴミ（デブリ）が発生し、社会問題になっていた。美しい宇宙を取り戻すことはできるのか？デブリの回収に奮闘する人々の物語。",
  "extra": {
    "番組内容": "ハチマキは全治１週間の怪我と診断され、治療のため月の病院に入院した。そこで彼は、かつて小惑星帯を初めて有人探査したベテラン航海士ハリー・ローランドの老いた姿と出会う。そしてもう一人、ノノという少女とも知り合いになる。その病院に１２年も滞在し、海に憧れをもつノノと九十九里浜生まれのハチマキはすっかり意気投合して語り合い、いっしょにカードゲームをするようになった。",
    "出演者": "【声】田中一成，雪野五月，折笠愛，こおろぎさとみ，秋元羊介，檜山修之，倉田雅世，鳥海勝美，百々麻子，三戸耕三，柳沢栄治，小林恭治",
    "原作・脚本": "【原作】幸村誠，【脚本】大河内一楼",
    "監督・演出": "【監督】谷口悟朗",
    "制作": "～サンライズ制作～"
  },
  "channel": {
    "type": "GR",
    "channel": "26",
    "name": "ＮＨＫＥテレ１東京",
    "id": "1i52rvs",
    "sid": 1032,
    "nid": 32737,
    "hasLogoData": true,
    "n": 2
  },
  "subTitle": "地球外少女",
  "episode": 7,
  "flags": [
    "字"
  ]
}
