{
  "id": "38224jvh8r",
  "category": "news",
  "title": "東京サイト",
  "fullTitle": "東京サイト　「東京洋傘」[字]",
  "detail": "昭和３５年創業の「東京洋傘」専門店モンブランヤマグチ。熟練の傘職人が絹、麻、綿などの素材で一本一本丁寧に作り上げている。その技術を見せてもらった。\n◇◇番組内容\n今後ますますの進化が期待される日本の首都・東京。この世界屈指の巨大都市の知られざる魅力を発見し、暮らしに役立つ最新情報をお届けします。\n◇◇ナビゲーター\n林家きく姫\n◇◇おしらせ\n☆番組ＨＰ\r\n　http://www.tv-asahi.co.jp/t-site/",
  "start": 1592196300000,
  "end": 1592196540000,
  "seconds": 240,
  "description": "昭和３５年創業の「東京洋傘」専門店モンブランヤマグチ。熟練の傘職人が絹、麻、綿などの素材で一本一本丁寧に作り上げている。その技術を見せてもらった。",
  "extra": {
    "◇番組内容": "今後ますますの進化が期待される日本の首都・東京。この世界屈指の巨大都市の知られざる魅力を発見し、暮らしに役立つ最新情報をお届けします。",
    "◇ナビゲーター": "林家きく姫",
    "◇おしらせ": "☆番組ＨＰ\r\n　http://www.tv-asahi.co.jp/t-site/"
  },
  "channel": {
    "type": "GR",
    "channel": "11",
    "name": "テレビ朝日",
    "id": "1i5bcjs",
    "sid": 1064,
    "nid": 32741,
    "hasLogoData": true,
    "n": 18
  },
  "subTitle": "東京洋傘",
  "episode": null,
  "flags": [
    "字"
  ]
}
