{
  "id": "381jqz0axu",
  "category": "drama",
  "title": "スクール・オブ・ロック",
  "fullTitle": "スクール・オブ・ロック（２１）「恋のトライアングル」[二][字]",
  "detail": "ロック魂全開の教師と名門校の生徒たちがバンドを組んだ！パワフル音楽コメディー。フレディのラブラブ話にサマーはやきもち！そんな中、フレディから内緒で呼び出され…。\n◇番組内容\nフレディへの告白に失敗したサマーだが、どうしても彼への思いをあきらめきれずにいた。だがフレディはケールとつきあっている。おまけにラブラブ話を聞かされ、サマーはやきもちばかり！そんな中、フレディから呼び出される。ケールには内緒だというが…。\n◇出演者\n【出演】ブレアナ・イーディー…佐倉綾音，ジェイド・ペティジョン…雨宮天，リカルド・ウルタド…梅原裕一郎，ランス・リム…畠中祐，エイダン・マイナー…西山宏太朗，トニー・カバレロ…神奈延年\n◇原作・脚本\n【脚本】ハリー・ハニガン\n◇監督・演出\n【演出】ジョナサン・ジャッジ\n◇制作\n～アメリカ・ニコロデオン制作～",
  "start": 1567243500000,
  "end": 1567245000000,
  "seconds": 1500,
  "description": "ロック魂全開の教師と名門校の生徒たちがバンドを組んだ！パワフル音楽コメディー。フレディのラブラブ話にサマーはやきもち！そんな中、フレディから内緒で呼び出され…。",
  "extra": {
    "番組内容": "フレディへの告白に失敗したサマーだが、どうしても彼への思いをあきらめきれずにいた。だがフレディはケールとつきあっている。おまけにラブラブ話を聞かされ、サマーはやきもちばかり！そんな中、フレディから呼び出される。ケールには内緒だというが…。",
    "出演者": "【出演】ブレアナ・イーディー…佐倉綾音，ジェイド・ペティジョン…雨宮天，リカルド・ウルタド…梅原裕一郎，ランス・リム…畠中祐，エイダン・マイナー…西山宏太朗，トニー・カバレロ…神奈延年",
    "原作・脚本": "【脚本】ハリー・ハニガン",
    "監督・演出": "【演出】ジョナサン・ジャッジ",
    "制作": "～アメリカ・ニコロデオン制作～"
  },
  "channel": {
    "type": "GR",
    "channel": "26",
    "name": "ＮＨＫＥテレ１東京",
    "id": "1i52rvs",
    "sid": 1032,
    "nid": 32737,
    "hasLogoData": true,
    "n": 2
  },
  "subTitle": "恋のトライアングル",
  "episode": 21,
  "flags": [
    "二",
    "字"
  ]
}
