{
  "id": "idt8axl",
  "category": "information",
  "title": "なないろ日和！【涼しげ＆上品に！小物で夏を楽しもう】",
  "fullTitle": "なないろ日和！【涼しげ＆上品に！小物で夏を楽しもう】",
  "detail": "▽時計とバッグも衣替え＆帽子選びのポイントは？おすすめリゾートコーデ🈀▽薬丸裕英と香坂みゆきのＭＣでお送りする『なにかいいことありそうな』生活情報番組",
  "start": 1684371540000,
  "end": 1684374900000,
  "seconds": 3360,
  "channel": {
    "type": "BS",
    "channel": "BS01_2",
    "name": "ＢＳテレ東２",
    "id": "8krw",
    "sid": 172,
    "nid": 4,
    "hasLogoData": false,
    "n": 55
  },
  "subTitle": "涼しげ＆上品に！小物で夏を楽しもう",
  "episode": 1,
  "flags": []
}
