{
  "id": "idozdc7",
  "category": "drama",
  "title": "【連続テレビ小説】虎に翼　第１週「女賢しくて牛売り損なう？」（１）",
  "fullTitle": "【連続テレビ小説】虎に翼　🈟第１週「女賢しくて牛売り損なう？」（１）🈖",
  "detail": "激動の昭和を生き抜いた五黄の寅年生まれの猪爪寅子（伊藤沙莉）。法という翼を手に入れ、女性初の弁護士、のちに裁判官となった女性とその仲間たちの物語が幕を開ける！",
  "start": 1711924200000,
  "end": 1711925100000,
  "seconds": 900,
  "channel": {
    "type": "BS",
    "channel": "BS15_0",
    "name": "ＮＨＫ　ＢＳ",
    "id": "8kpx",
    "sid": 101,
    "nid": 4,
    "hasLogoData": true,
    "n": 41
  },
  "subTitle": "女賢しくて牛売り損なう？",
  "episode": 1,
  "flags": [
    "新",
    "解"
  ]
}
