{
  "id": "w68lahr",
  "category": "hobby",
  "title": "カウンティング・カーズS3 #61 思い出の名車登場！特製カレンダー撮影会",
  "fullTitle": "カウンティング・カーズS3 #61 思い出の名車登場！特製カレンダー撮影会🈔",
  "detail": "『#61 思い出の名車登場！特製カレンダー撮影会』\r\nカウンツ・カスタムズのカレンダー用写真の撮影日。メンバーがそれぞれ選んだお気に入りのドリームカーが集結する！",
  "start": 1653602400000,
  "end": 1653604200000,
  "seconds": 1800,
  "channel": {
    "type": "CS",
    "channel": "CS14",
    "name": "ヒストリーチャンネル",
    "id": "f0dy",
    "sid": 342,
    "nid": 7,
    "hasLogoData": true,
    "n": 134
  },
  "subTitle": "思い出の名車登場！特製カレンダー撮影会🈔",
  "episode": 61,
  "flags": [
    "二"
  ]
}
