{
  "id": "idtv86a",
  "category": "variety",
  "title": "サンド道楽＃32／3組の超個性派ピン芸人達が若返り！滝行＆最新エステで絶叫！？",
  "fullTitle": "サンド道楽＃32／3組の超個性派ピン芸人達が若返り！滝行＆最新エステで絶叫！？",
  "detail": "サンドと同世代のアラフィフピン芸人3組が「若返り」道楽を提案▽高さ23mからの衝撃水圧！過酷な滝行＆最新エステで絶叫！？\r\n",
  "start": 1660483800000,
  "end": 1660485600000,
  "seconds": 1800,
  "channel": {
    "type": "BS",
    "channel": "BS13_1",
    "name": "ＢＳフジ・１８３",
    "id": "8ks7",
    "sid": 183,
    "nid": 4,
    "hasLogoData": false,
    "n": 59
  },
  "subTitle": "若返り",
  "episode": 32,
  "flags": []
}
