{
  "id": "w68grzr",
  "category": "documentary",
  "title": "クリエイターとその愉快な仲間たち：ゲスト：宮島竜治・小林聖太郎",
  "fullTitle": "クリエイターとその愉快な仲間たち：ゲスト：宮島竜治・小林聖太郎(日)",
  "detail": "映画編集者の宮島竜治さんとその仲間、映画監督の小林聖太郎さんをゲストに迎えて、その発想の種に迫ります。",
  "start": 1634256000000,
  "end": 1634257800000,
  "seconds": 1800,
  "channel": {
    "type": "CS",
    "channel": "CS6",
    "name": "ディスカバリー",
    "id": "f0dw",
    "sid": 340,
    "nid": 7,
    "hasLogoData": true,
    "n": 132
  },
  "subTitle": "",
  "episode": null,
  "flags": []
}
