{
  "id": "38224jveon",
  "category": "variety",
  "title": "キョコロヒー　もしものピンチをどう乗り切る⁉対策会議＆楽曲プロジェクト新展開",
  "fullTitle": "キョコロヒー　もしものピンチをどう乗り切る⁉対策会議＆楽曲プロジェクト新展開🈑",
  "detail": "日向坂46齊藤京子と芸人ヒコロヒーによる凸凹トークバラエティ。自由過ぎるアイドルと翻弄される芸人のトークがなぜかクセになってしまうと評判のヘンテコ番組です。\n◇◇出演者\n齊藤京子（日向坂46）\r\nヒコロヒー\n◇◇おしらせ\n☆番組ＨＰ\r\n　https://www.tv-asahi.co.jp/Kyoccorohee/\n◇◇番組内容\n◆緊急事態に備えよう！もしものピンチ対策会議\r\n生放送に大遅刻！？大先輩の悪口を本人に聞かれちゃった！…など、\r\n芸能界の大ピンチをどう乗り切るか！？\r\nファーストサマーウイカと一緒に対策法を考える！\r\nさらに！芸能界の大先輩！勝俣州和のお役立ちアドバイスも！！\n◇◇番組内容２\n◆キョコロヒー楽曲プロジェクトに新展開！\r\n秋元康×齊藤京子×ヒコロヒー緊急会議！\r\nサプライズ！まさかの協力者の名前発表にテンション爆上がり！？\n◇◇出演者２\nファーストサマーウイカ\r\n秋元康",
  "start": 1696257900000,
  "end": 1696259700000,
  "seconds": 1800,
  "description": "日向坂46齊藤京子と芸人ヒコロヒーによる凸凹トークバラエティ。自由過ぎるアイドルと翻弄される芸人のトークがなぜかクセになってしまうと評判のヘンテコ番組です。",
  "extra": {
    "◇出演者": "齊藤京子（日向坂46）\r\nヒコロヒー",
    "◇おしらせ": "☆番組ＨＰ\r\n　https://www.tv-asahi.co.jp/Kyoccorohee/",
    "◇番組内容": "◆緊急事態に備えよう！もしものピンチ対策会議\r\n生放送に大遅刻！？大先輩の悪口を本人に聞かれちゃった！…など、\r\n芸能界の大ピンチをどう乗り切るか！？\r\nファーストサマーウイカと一緒に対策法を考える！\r\nさらに！芸能界の大先輩！勝俣州和のお役立ちアドバイスも！！",
    "◇番組内容２": "◆キョコロヒー楽曲プロジェクトに新展開！\r\n秋元康×齊藤京子×ヒコロヒー緊急会議！\r\nサプライズ！まさかの協力者の名前発表にテンション爆上がり！？",
    "◇出演者２": "ファーストサマーウイカ\r\n秋元康"
  },
  "channel": {
    "type": "GR",
    "channel": "24",
    "name": "テレビ朝日",
    "id": "1i5bcjs",
    "sid": 1064,
    "nid": 32741,
    "hasLogoData": true,
    "n": 20
  },
  "subTitle": "",
  "episode": 1,
  "flags": [
    "字"
  ]
}
