{
  "id": "idso9r7",
  "category": "sports",
  "title": "新春！ゴルフバトルＳＰ～五輪メダリスト×女子プロ×最強ゴルフ芸人～",
  "fullTitle": "新春！ゴルフバトルＳＰ～五輪メダリスト×女子プロ×最強ゴルフ芸人～",
  "detail": "スポーツ界のレジェンド『五輪メダリスト』、優勝経験のある『女子プロゴルファー』、実力者揃いの『最強ゴルフ芸人』がチームを作り“真剣ゴルフバトル”を繰り広げます！",
  "start": 1647770400000,
  "end": 1647777240000,
  "seconds": 6840,
  "channel": {
    "type": "BS",
    "channel": "BS01_1",
    "name": "ＢＳ－ＴＢＳ",
    "id": "8krn",
    "sid": 163,
    "nid": 4,
    "hasLogoData": true,
    "n": 52
  },
  "subTitle": "",
  "episode": 1,
  "flags": []
}
