{
  "id": "38224jvfv1",
  "category": "information",
  "title": "羽鳥慎一モーニングショー",
  "fullTitle": "羽鳥慎一モーニングショー🈑",
  "detail": "速報!!大谷が今永と初対決!!「逆境から復活」秘話▽待ちわびた!!「桜満開」 公園に川辺に花見殺到 泥酔・搬送・ポイ捨て　「迷惑客」トラブルも\n◇◇番組内容\n羽鳥慎一が毎日の様々なニュースを、分かりやすくお伝えします。暮らしをよりよくする情報はもちろん、難しいことは何が問題なのか、パネルを駆使して読み解きます。\n◇◇出演者\n【司会】\r\n羽鳥慎一\r\n【アシスタント】\r\n松岡朱里（テレビ朝日アナウンサー）\n◇◇おしらせ\n☆番組ＨＰ\r\n　http://www.tv-asahi.co.jp/m-show/\r\n\r\n※放送内容が変更になる場合があります、予めご了承ください。",
  "start": 1712530800000,
  "end": 1712537700000,
  "seconds": 6900,
  "description": "速報!!大谷が今永と初対決!!「逆境から復活」秘話▽待ちわびた!!「桜満開」 公園に川辺に花見殺到 泥酔・搬送・ポイ捨て　「迷惑客」トラブルも",
  "extra": {
    "◇番組内容": "羽鳥慎一が毎日の様々なニュースを、分かりやすくお伝えします。暮らしをよりよくする情報はもちろん、難しいことは何が問題なのか、パネルを駆使して読み解きます。",
    "◇出演者": "【司会】\r\n羽鳥慎一\r\n【アシスタント】\r\n松岡朱里（テレビ朝日アナウンサー）",
    "◇おしらせ": "☆番組ＨＰ\r\n　http://www.tv-asahi.co.jp/m-show/\r\n\r\n※放送内容が変更になる場合があります、予めご了承ください。"
  },
  "channel": {
    "type": "GR",
    "channel": "24",
    "name": "テレビ朝日",
    "id": "1i5bcjs",
    "sid": 1064,
    "nid": 32741,
    "hasLogoData": true,
    "n": 20
  },
  "subTitle": "",
  "episode": 1,
  "flags": [
    "字"
  ]
}
