{
  "id": "3826py3c8w",
  "category": "sports",
  "title": "みんなのスポーツ▽満票ＭＶＰ大谷を知る名将が語る二刀流＆パリ五輪メダル期待の新星",
  "fullTitle": "みんなのスポーツ▽満票ＭＶＰ大谷を知る名将が語る二刀流＆パリ五輪メダル期待の新星",
  "detail": "満票で２度目のＭＶＰを獲得した大谷翔平。１回目のＭＶＰ獲得時にエンゼルスの監督を務めたマドンが語る大谷の二刀流。パリ五輪メダル期待の新星！クライミング安楽特集",
  "start": 1700402040000,
  "end": 1700404200000,
  "seconds": 2160,
  "channel": {
    "type": "GR",
    "channel": "23",
    "name": "テレビ東京１",
    "id": "1i5dhps",
    "sid": 1072,
    "nid": 32742,
    "hasLogoData": true,
    "n": 27
  },
  "subTitle": "",
  "episode": 1,
  "flags": []
}
