{
  "id": "36h6jr1jb4",
  "category": "information",
  "title": "関ジャニ∞のジャニ勉",
  "fullTitle": "関ジャニ∞のジャニ勉[Ｓ]",
  "detail": "「ゲスト」の“頑固道”をテーマに徹底討論！お笑い第７世代筆頭のハナコが初登場！仲良しトリオが互いの不満爆発で解散危機！？初出し秋山の恥ずかしすぎる映像公開！\n◇番組内容\n結成わずか４年でキングオブコントを制し、冠番組やドラマ出演など今最も勢いのある実力派コント師ハナコが絶対に譲れないちょっと変わった頑固な一面「頑固道」を徹底的に語りまくる！\n◇出演者\n【関ジャニ∞】横山裕　村上信五　丸山隆平　安田章大【ゲスト】ハナコ",
  "start": 1618826400000,
  "end": 1618829700000,
  "seconds": 3300,
  "description": "「ゲスト」の“頑固道”をテーマに徹底討論！お笑い第７世代筆頭のハナコが初登場！仲良しトリオが互いの不満爆発で解散危機！？初出し秋山の恥ずかしすぎる映像公開！",
  "extra": {
    "番組内容": "結成わずか４年でキングオブコントを制し、冠番組やドラマ出演など今最も勢いのある実力派コント師ハナコが絶対に譲れないちょっと変わった頑固な一面「頑固道」を徹底的に語りまくる！",
    "出演者": "【関ジャニ∞】横山裕　村上信五　丸山隆平　安田章大【ゲスト】ハナコ"
  },
  "channel": {
    "type": "GR",
    "channel": "32",
    "name": "テレ玉１",
    "id": "1hes13s",
    "sid": 29752,
    "nid": 32295,
    "hasLogoData": true,
    "n": 12
  },
  "subTitle": "ゲスト",
  "episode": null,
  "flags": []
}
