{"id":"381ocd7ved","category":"information","title":"Ｓｔｏｒｉｅｓ　～あなたのライフを探す家～","fullTitle":"Ｓｔｏｒｉｅｓ　～あなたのライフを探す家～[字]","detail":"自分らしく生きている人にスポットをあて、仕事や生活を紹介しながら今へと繋がるターニングポイントを紐解きます。そして“ライフストーリーで大切にしていること”とは？\n◇出演者\n【出演】渡辺正寿（セルフビルドパートナー）\r\n【ナレーター】ホラン千秋\n◇番組内容\n実際に設計から現場で自分で家を建てる「セルフビルド」をサポートする、渡辺正寿。今、ここ数年のＤＩＹブームを受け、「手作り感のある家」を作りたい人が増えている。設計段階から依頼者と打ち合わせを重ね、建築現場でも一緒に作業して希望通りに完成するよう尽力する。\r\n”手作り感のある家作り”の難しさを実感した彼ならではの人生ストーリーで大切にしていることとは？\n◇監督・演出\n福島伸次郎","start":1563026040000,"end":1563026400000,"seconds":360,"description":"自分らしく生きている人にスポットをあて、仕事や生活を紹介しながら今へと繋がるターニングポイントを紐解きます。そして“ライフストーリーで大切にしていること”とは？","extra":{"出演者":"【出演】渡辺正寿（セルフビルドパートナー）\r\n【ナレーター】ホラン千秋","番組内容":"実際に設計から現場で自分で家を建てる「セルフビルド」をサポートする、渡辺正寿。今、ここ数年のＤＩＹブームを受け、「手作り感のある家」を作りたい人が増えている。設計段階から依頼者と打ち合わせを重ね、建築現場でも一緒に作業して希望通りに完成するよう尽力する。\r\n”手作り感のある家作り”の難しさを実感した彼ならではの人生ストーリーで大切にしていることとは？","監督・演出":"福島伸次郎"},"channel":{"type":"GR","channel":"25","name":"日テレ１","id":"1i54x1s","sid":1040,"nid":32738,"hasLogoData":true,"n":15},"subTitle":"","episode":null,"flags":["字"]}
