{
  "id": "ids2wyk",
  "category": "information",
  "title": "大改造！！劇的ビフォーアフター　「床下に川が流れる家」",
  "fullTitle": "🈑大改造！！劇的ビフォーアフター　「床下に川が流れる家」",
  "detail": "83歳母が雨におびえる日々…床下の川が氾濫!?築113年の危険な家を予算800万で大変身！節約リフォーム術が続々！夢の御殿完成に、感動の涙“まるで旅館みたい！”",
  "start": 1717916400000,
  "end": 1717920000000,
  "seconds": 3600,
  "channel": {
    "type": "BS",
    "channel": "BS01_3",
    "name": "ＢＳ朝日３",
    "id": "8krd",
    "sid": 153,
    "nid": 4,
    "hasLogoData": true,
    "n": 50
  },
  "subTitle": "床下に川が流れる家",
  "episode": 1,
  "flags": [
    "字"
  ]
}
