{
  "id": "381ocd7vr8",
  "category": "variety",
  "title": "おしゃれクリップ…黒木メイサが語る子供と家族への思い▼4姉妹の長女から手紙",
  "fullTitle": "おしゃれクリップ🈑…黒木メイサが語る子供と家族への思い▼4姉妹の長女から手紙",
  "detail": "超久々に日テレカムバック！デビュー20周年・黒木メイサ▼4姉妹の長女から手紙▼意外な友人!?宮川大輔が暴露！海外旅行で見せた黒木の素顔▼「日本を制覇したい」とは\n◇出演者\n【ＭＣ】山崎育三郎、井桁弘恵\r\n【ゲスト】黒木メイサ\r\n【VTR出演】宮川大輔\n◇番組内容\n超久々に日テレカムバック！デビュー20周年・黒木メイサ▼子供と家族への思い…宝物は亡き父の形見▼幼い頃はケンカばかりだった…4姉妹の長女から手紙▼意外な友人？宮川大輔が暴露！旅行で見せた黒木の素顔▼ハワイ、そして、ＬＡ生活「初めてＳＮＳでナンパをした」その相手とは？▼今は日本を制覇したい！▼おしゃれジュエリーを付けている方に聞いた！「お値段教えて下さい」▼黒木メイサの謎に満ちたおよそ10年間に迫る",
  "start": 1720357200000,
  "end": 1720359000000,
  "seconds": 1800,
  "description": "超久々に日テレカムバック！デビュー20周年・黒木メイサ▼4姉妹の長女から手紙▼意外な友人!?宮川大輔が暴露！海外旅行で見せた黒木の素顔▼「日本を制覇したい」とは",
  "extra": {
    "出演者": "【ＭＣ】山崎育三郎、井桁弘恵\r\n【ゲスト】黒木メイサ\r\n【VTR出演】宮川大輔",
    "番組内容": "超久々に日テレカムバック！デビュー20周年・黒木メイサ▼子供と家族への思い…宝物は亡き父の形見▼幼い頃はケンカばかりだった…4姉妹の長女から手紙▼意外な友人？宮川大輔が暴露！旅行で見せた黒木の素顔▼ハワイ、そして、ＬＡ生活「初めてＳＮＳでナンパをした」その相手とは？▼今は日本を制覇したい！▼おしゃれジュエリーを付けている方に聞いた！「お値段教えて下さい」▼黒木メイサの謎に満ちたおよそ10年間に迫る"
  },
  "channel": {
    "type": "GR",
    "channel": "25",
    "name": "日テレ１",
    "id": "1i54x1s",
    "sid": 1040,
    "nid": 32738,
    "hasLogoData": true,
    "n": 17
  },
  "subTitle": "日本を制覇したい",
  "episode": 1,
  "flags": [
    "字"
  ]
}
